__init__.py
redemais/__init__.py
redemais/whitelabel/__init__.py
redemais/whitelabel/api.py
redemais/whitelabel/apis/__init__.py
redemais/whitelabel/apis/beneficiarios.py
redemais/whitelabel/dtos/__init__.py
redemais/whitelabel/dtos/beneficiario.py
redemais_white_label_python_sdk-1.0.1.dist-info/licenses/LICENSE
redemais_white_label_python_sdk-1.0.1.dist-info/METADATA
redemais_white_label_python_sdk-1.0.1.dist-info/WHEEL
redemais_white_label_python_sdk-1.0.1.dist-info/top_level.txt
redemais_white_label_python_sdk-1.0.1.dist-info/RECORD
